MANIFEST.in
setup.py
static/VERSION
static/__init__.py
static/apps.py
static/cli.py
static.egg-info/PKG-INFO
static.egg-info/SOURCES.txt
static.egg-info/dependency_links.txt
static.egg-info/entry_points.txt
static.egg-info/requires.txt
static.egg-info/top_level.txt